{
  "path_elements": [
    {
      "type": "waypoint",
      "translation_target": {
        "x_meters": 0.367,
        "y_meters": 7.273,
        "intermediate_handoff_radius_meters": 0.2
      },
      "rotation_target": {
        "rotation_radians": 1.5707963267948966,
        "profiled_rotation": true
      }
    },
    {
      "type": "waypoint",
      "translation_target": {
        "x_meters": 1.84212032095949,
        "y_meters": 7.204243030060217,
        "intermediate_handoff_radius_meters": 0.2
      },
      "rotation_target": {
        "rotation_radians": 0.0,
        "profiled_rotation": true
      }
    }
  ],
  "constraints": {
    "max_velocity_meters_per_sec": [
      {
        "value": 2.0,
        "start_ordinal": 0,
        "end_ordinal": 1
      }
    ]
  }
}